poethepoet/__init__.py
poethepoet/__main__.py
poethepoet/__version__.py
poethepoet/app.py
poethepoet/completion/__init__.py
poethepoet/completion/bash.py
poethepoet/completion/fish.py
poethepoet/completion/zsh.py
poethepoet/config/__init__.py
poethepoet/config/config.py
poethepoet/config/file.py
poethepoet/config/partition.py
poethepoet/config/primitives.py
poethepoet/context.py
poethepoet/env/__init__.py
poethepoet/env/cache.py
poethepoet/env/manager.py
poethepoet/env/parse.py
poethepoet/env/template.py
poethepoet/exceptions.py
poethepoet/executor/__init__.py
poethepoet/executor/base.py
poethepoet/executor/poetry.py
poethepoet/executor/simple.py
poethepoet/executor/task_run.py
poethepoet/executor/uv.py
poethepoet/executor/virtualenv.py
poethepoet/helpers/__init__.py
poethepoet/helpers/command/__init__.py
poethepoet/helpers/command/ast.py
poethepoet/helpers/command/ast_core.py
poethepoet/helpers/eventloop.py
poethepoet/helpers/git.py
poethepoet/helpers/python.py
poethepoet/helpers/script.py
poethepoet/io.py
poethepoet/options/__init__.py
poethepoet/options/annotations.py
poethepoet/options/base.py
poethepoet/plugin.py
poethepoet/scripts/__init__.py
poethepoet/scripts/_rm.py
poethepoet/shutdown.py
poethepoet/task/__init__.py
poethepoet/task/args.py
poethepoet/task/base.py
poethepoet/task/cmd.py
poethepoet/task/expr.py
poethepoet/task/graph.py
poethepoet/task/parallel.py
poethepoet/task/ref.py
poethepoet/task/script.py
poethepoet/task/sequence.py
poethepoet/task/shell.py
poethepoet/task/switch.py
poethepoet/ui.py
poethepoet/virtualenv.py
poethepoet-0.40.0.dist-info/METADATA
poethepoet-0.40.0.dist-info/WHEEL
poethepoet-0.40.0.dist-info/entry_points.txt
poethepoet-0.40.0.dist-info/licenses/LICENSE
poethepoet-0.40.0.dist-info/RECORD
